HISTORY.rst
LICENSE.txt
MANIFEST.in
README.rst
setup.cfg
setup.py
docs/Makefile
docs/conf.py
docs/configuration.rst
docs/dynamic-content.rst
docs/index.rst
docs/make.bat
docs/quickstart.rst
docs/useful-methods.rst
minipyp/__init__.py
minipyp/minipyp.py
minipyp.egg-info/PKG-INFO
minipyp.egg-info/SOURCES.txt
minipyp.egg-info/dependency_links.txt
minipyp.egg-info/entry_points.txt
minipyp.egg-info/requires.txt
minipyp.egg-info/top_level.txt
tests/test_minipyp.py
tests/root/index.py