Metadata-Version: 1.2
Name: minipyp
Version: 0.2.0a1
Summary: A more traditional web server
Home-page: https://minipyp.readthedocs.io/en/latest/
Author: Ryan Garber
Author-email: ryanmichaelgarber@gmail.com
License: UNKNOWN
Download-URL: https://github.com/RyanGarber/minipyp/archive/0.2.0a1.tar.gz
Keywords: http https web cgi fast-cgi fpm ssl tls socket proxy reverse
Platform: UNKNOWN
Classifier: Development Status :: 3 - Alpha
Classifier: License :: OSI Approved :: MIT License
Classifier: Topic :: Internet :: WWW/HTTP :: HTTP Servers
Classifier: Natural Language :: English
Classifier: Intended Audience :: System Administrators
Classifier: Programming Language :: Python :: 3.4
Classifier: Programming Language :: Python :: 3.5
Classifier: Programming Language :: Python :: 3.6
Classifier: Programming Language :: Python :: 3.7
Requires-Python: >=3
